osm_login_python/__init__.py
osm_login_python/__version__.py
osm_login_python/core.py
osm_login_python-2.1.0.dist-info/METADATA
osm_login_python-2.1.0.dist-info/WHEEL
osm_login_python-2.1.0.dist-info/licenses/LICENSE
osm_login_python-2.1.0.dist-info/RECORD
