Metadata-Version: 2.4
Name: osm-login-python
Version: 2.1.0
Summary: Package to manage OAuth 2.0 login for OSM in Python.
Project-URL: homepage, https://hotosm.github.io/osm-login-python
Project-URL: documentation, https://hotosm.github.io/osm-login-python
Project-URL: repository, https://github.com/hotosm/osm-login-python
Author-email: Kshitij Raj Sharma <skshitizraj@gmail.com>, Sam Woodcock <sam.woodcock@protonmail.com>
License: GPL-3.0-only
License-File: LICENSE
Keywords: hot,login,oauth2,openstreetmap,osm
Classifier: Programming Language :: Python :: 3
Classifier: Programming Language :: Python :: 3.10
Classifier: Programming Language :: Python :: 3.11
Classifier: Programming Language :: Python :: 3.12
Classifier: Programming Language :: Python :: 3.13
Classifier: Topic :: Scientific/Engineering :: GIS
Classifier: Topic :: Utilities
Requires-Python: >=3.9
Requires-Dist: itsdangerous>=2.0.0
Requires-Dist: requests-oauthlib>=1.3.0
Provides-Extra: docs
Requires-Dist: mkdocs-exclude>=1.0.2; extra == 'docs'
Requires-Dist: mkdocs-material>=9.4.2; extra == 'docs'
Requires-Dist: mkdocs>=1.5.3; extra == 'docs'
Requires-Dist: mkdocstrings-python>=1.7.0; extra == 'docs'
Provides-Extra: test
Requires-Dist: coverage-badge>=1.1.2; extra == 'test'
Requires-Dist: coverage>=7.6.1; extra == 'test'
Requires-Dist: pytest-mock>=3.14.0; extra == 'test'
Requires-Dist: pytest>=7.4.2; extra == 'test'
